fabric/dataagent/__init__.py
fabric/dataagent/client/__init__.py
fabric/dataagent/client/_create_delete.py
fabric/dataagent/client/_datasource.py
fabric/dataagent/client/_fabric_data_agent_api.py
fabric/dataagent/client/_fabric_data_agent_mgmt.py
fabric/dataagent/client/_fabric_openai.py
fabric/dataagent/client/_tagged_value.py
fabric/dataagent/client/_util.py
fabric/dataagent/datasources/__init__.py
fabric/dataagent/datasources/base.py
fabric/dataagent/datasources/factory.py
fabric/dataagent/datasources/kustodb.py
fabric/dataagent/datasources/lakehouse.py
fabric/dataagent/datasources/ontology.py
fabric/dataagent/datasources/semantic_model.py
fabric/dataagent/datasources/warehouse.py
fabric/dataagent/evaluation/__init__.py
fabric/dataagent/evaluation/_display.py
fabric/dataagent/evaluation/_evaluation_runner.py
fabric/dataagent/evaluation/_few_shot_validation.py
fabric/dataagent/evaluation/_models.py
fabric/dataagent/evaluation/_storage.py
fabric/dataagent/evaluation/_thread.py
fabric/dataagent/evaluation/_utils.py
fabric/dataagent/evaluation/core.py
fabric/dataagent/evaluation/ground_truth.py
fabric/dataagent/evaluation/report.py
fabric_data_agent_sdk-0.1.17a0.dist-info/licenses/LICENSE
fabric_data_agent_sdk-0.1.17a0.dist-info/METADATA
fabric_data_agent_sdk-0.1.17a0.dist-info/WHEEL
fabric_data_agent_sdk-0.1.17a0.dist-info/top_level.txt
fabric_data_agent_sdk-0.1.17a0.dist-info/RECORD
