Metadata-Version: 2.4
Name: fabric-data-agent-sdk
Version: 0.1.17a0
Summary: SDK for the Fabric Data Agent Library
Author: Microsoft Corporation
License: MIT License
Project-URL: Repository, https://msdata.visualstudio.com/DefaultCollection/A365/_git/SynapseML-Agent-SDK
Classifier: Development Status :: 3 - Alpha
Classifier: Intended Audience :: Developers
Classifier: Intended Audience :: Education
Classifier: Intended Audience :: Science/Research
Classifier: Programming Language :: Python :: 3.10
Classifier: Programming Language :: Python :: 3 :: Only
Requires-Python: <3.13,>=3.10
License-File: LICENSE
Requires-Dist: semantic-link-sempy>=0.8.0
Requires-Dist: openai>=1.57.0
Requires-Dist: httpx==0.27.2
Requires-Dist: semantic-link-labs==0.9.10
Requires-Dist: azure-kusto-data>=4.5.0
Requires-Dist: azure-identity==1.17.1
Requires-Dist: markdown2==2.5.3
Requires-Dist: tabulate>=0.9.0
Provides-Extra: test
Requires-Dist: pyspark==3.5.1; extra == "test"
Requires-Dist: azure-storage-blob==12.20.0; extra == "test"
Requires-Dist: pytest==8.2.1; extra == "test"
Requires-Dist: pytest-cov==5.0.0; extra == "test"
Requires-Dist: python-dotenv==1.0.1; extra == "test"
Requires-Dist: papermill==2.6.0; extra == "test"
Requires-Dist: ipykernel==6.29.4; extra == "test"
Requires-Dist: requests-mock==1.12.1; extra == "test"
Requires-Dist: pyjwt==2.9.0; extra == "test"
Requires-Dist: synapseml-utils==1.0.26; extra == "test"
Requires-Dist: azure-identity==1.17.1; extra == "test"
Requires-Dist: azure-keyvault-secrets==4.8.0; extra == "test"
Requires-Dist: semantic-link-labs==0.9.10; extra == "test"
Requires-Dist: jinja2==3.1.6; extra == "test"
Requires-Dist: markupsafe==3.0.2; extra == "test"
Provides-Extra: dev
Requires-Dist: black[jupyter]; extra == "dev"
Dynamic: license-file
